eure/__init__.py
eure/eure.cpython-38-arm-linux-gnueabihf.so
eure-0.0.0.dist-info/METADATA
eure-0.0.0.dist-info/WHEEL
eure.libs/libgcc_s-262c4f60.so.1
eure-0.0.0.dist-info/RECORD
